{
  "date": "2026-07-08",
  "generated_at": "2026-07-08T03:51:59.745365+00:00",
  "source": "rss-auto",
  "releases": [
    {
      "name_cn": "地狱潜兵:越南",
      "name_en": "Hell Let Loose: Vietnam",
      "date": "2026-06-18",
      "platforms": [
        "PC",
        "PS5",
        "Xbox"
      ],
      "studio": "Team17 / Expression Games",
      "genre": [
        "硬核射击",
        "二战军事",
        "多人"
      ],
      "summary": "硬核多人战争射击《地狱潜兵》系列新作,这次把战场搬到越战丛林。强调真实弹道、班组协作与大地图阵地战,适合喜欢拟真军事对抗的玩家。",
      "hype": "🔥"
    },
    {
      "name_cn": "EA 综合格斗 6",
      "name_en": "EA Sports UFC 6",
      "date": "2026-06-19",
      "platforms": [
        "PS5",
        "Xbox"
      ],
      "studio": "EA Vancouver",
      "genre": [
        "格斗",
        "体育竞技"
      ],
      "summary": "EA 旗下 UFC 综合格斗游戏时隔多年回归,全新动作捕捉与受击反馈系统,真实还原八角笼里的擒抱、地面缠斗与重拳 KO。",
      "hype": "🔥"
    },
    {
      "name_cn": "转生之兽",
      "name_en": "Beast of Reincarnation",
      "date": "2026-08-04",
      "platforms": [
        "PC",
        "PS5"
      ],
      "studio": "Game Freak",
      "genre": [
        "动作 RPG",
        "魂类"
      ],
      "summary": "宝可梦开发商 Game Freak 罕见的新原创动作 RPG,末世废土与神兽题材结合的魂系动作冒险,是工作室尝试主机硬核大作的重要一步。",
      "hype": "🔥🔥"
    },
    {
      "name_cn": "晨行者之血",
      "name_en": "The Blood of Dawnwalker",
      "date": "2026-09-03",
      "platforms": [
        "PC",
        "PS5",
        "Xbox"
      ],
      "studio": "Rebel Wolves",
      "genre": [
        "开放世界 RPG",
        "吸血鬼",
        "黑暗奇幻"
      ],
      "summary": "由《巫师3》核心团队成立的新工作室 Rebel Wolves 打造的开放世界 RPG,玩家扮演半人半吸血鬼,昼夜切换不同能力,主打成熟叙事与道德抉择。",
      "hype": "🔥🔥🔥"
    },
    {
      "name_cn": "漫威金刚狼",
      "name_en": "Marvel's Wolverine",
      "date": "2026-09-15",
      "platforms": [
        "PS5"
      ],
      "studio": "Insomniac Games",
      "genre": [
        "动作冒险",
        "漫威英雄"
      ],
      "summary": "《漫威蜘蛛侠》开发商 Insomniac 操刀的金刚狼独占大作,血腥近战、利爪暴走与硬汉叙事,是 PS5 平台最受期待的单机动作游戏之一。",
      "hype": "🔥🔥🔥"
    },
    {
      "name_cn": "空之轨迹 第二章",
      "name_en": "The Legend of Heroes: Trails in the Sky 2nd Chapter",
      "date": "2026-09-17",
      "platforms": [
        "PC",
        "PS5",
        "Switch"
      ],
      "studio": "Falcom",
      "genre": [
        "日式 RPG",
        "回合制"
      ],
      "summary": "经典日式 RPG《空之轨迹》系列重制续作,延续艾丝蒂尔的冒险旅程,画面与战斗全面现代化,是轨迹系列老玩家的情怀之作。",
      "hype": "🔥🔥"
    },
    {
      "name_cn": "控制:共鸣",
      "name_en": "Control Resonant",
      "date": "2026-09-24",
      "platforms": [
        "PC",
        "PS5",
        "Xbox"
      ],
      "studio": "Remedy Entertainment",
      "genre": [
        "动作冒险",
        "超自然",
        "TPS"
      ],
      "summary": "Remedy 旗下《控制》系列正统续作,延续超自然管理局的诡谲世界观,主角重返「最古老的房子」对抗失控异象。超能力战斗、扭曲建筑与意识流叙事是看点。",
      "hype": "🔥🔥🔥"
    },
    {
      "name_cn": "鬼武者:刀之道",
      "name_en": "Onimusha: Way of the Sword",
      "date": "2026-09-25",
      "platforms": [
        "PC",
        "PS5",
        "Xbox"
      ],
      "studio": "Capcom",
      "genre": [
        "动作",
        "战国",
        "武士"
      ],
      "summary": "卡普空经典《鬼武者》系列时隔近二十年的全新正传,以战国乱世为背景,主打一闪居合的硬核武士斩杀,RE 引擎打造的高质感画面备受期待。",
      "hype": "🔥🔥🔥"
    },
    {
      "name_cn": "雷曼传奇:重述",
      "name_en": "Rayman Legends Retold",
      "date": "2026-10-01",
      "platforms": [
        "PC",
        "PS5",
        "Xbox",
        "Switch"
      ],
      "studio": "Ubisoft",
      "genre": [
        "平台跳跃",
        "横版"
      ],
      "summary": "育碧经典横版动作《雷曼传奇》的重制版,高清重绘画面、新增关卡与本地多人合作,是适合全家同乐的轻松平台跳跃佳作。",
      "hype": "🔥🔥"
    },
    {
      "name_cn": "使命召唤:现代战争 4",
      "name_en": "Call of Duty: Modern Warfare 4",
      "date": "2026-10-23",
      "platforms": [
        "PC",
        "PS5",
        "Xbox"
      ],
      "studio": "Infinity Ward / Activision",
      "genre": [
        "第一人称射击",
        "军事"
      ],
      "summary": "年货射击巨头《使命召唤》现代战争系列新作,延续 141 特遣队的故事线,电影化战役、多人对战与战区模式三件套,FPS 玩家年度焦点。",
      "hype": "🔥🔥"
    },
    {
      "name_cn": "影刃零",
      "name_en": "Phantom Blade Zero",
      "date": "2026-10-29",
      "platforms": [
        "PC",
        "PS5"
      ],
      "studio": "S-GAME (上海梁其伟工作室)",
      "genre": [
        "动作",
        "武侠",
        "暗黑武侠"
      ],
      "summary": "国产 3A 期待之作,融合武侠与暗黑奇幻的「武侠朋克」动作游戏,行云流水的刀剑连招与高难度战斗,被视为国产单机冲击主机市场的代表作。",
      "hype": "🔥🔥🔥"
    },
    {
      "name_cn": "侠盗猎车手 6",
      "name_en": "Grand Theft Auto VI",
      "date": "2026-11-19",
      "platforms": [
        "PS5",
        "Xbox"
      ],
      "studio": "Rockstar Games",
      "genre": [
        "开放世界",
        "动作",
        "犯罪"
      ],
      "summary": "游戏史上最受瞩目的开放世界续作,重返虚构的莱昂尼达州(罪恶都市原型),双主角剧情、空前规模的活世界与互动细节,被业界视为时代级别大作。",
      "hype": "🔥🔥🔥"
    },
    {
      "name_cn": "战争机器:决战日",
      "name_en": "Gears of War: E-Day",
      "date": "2026 待定",
      "platforms": [
        "PC",
        "Xbox"
      ],
      "studio": "The Coalition / Xbox",
      "genre": [
        "第三人称射击",
        "科幻"
      ],
      "summary": "《战争机器》系列前传,回到「灾变日」这场人类对抗兽族的灾难起点,年轻的马库斯与多姆并肩作战,是 Xbox 第一方重磅射击大作。",
      "hype": "🔥🔥"
    }
  ],
  "hot": [
    {
      "title": "Crimson Desert Dev Working On Getting Switch 2 Version Up An",
      "category": "游戏更新",
      "summary": "\"To a level where basic gameplay is possible\".Earlier this year, South Korean publisher and developer Pearl Abyss began \"research and development\" on a Switch 2 version of its new open-world action-adventure Crimson Desert.The CEO Heo Jin-Young has now shared an update during the",
      "source": "Nintendo Life",
      "url": "https://www.nintendolife.com/news/2026/07/crimson-desert-dev-working-on-getting-switch-2-version-up-and-running"
    },
    {
      "title": "Task Bar Hero class tier list and the best team compositions",
      "category": "重磅新闻",
      "summary": "Keep Ranger your priority and everything else will fall into place.",
      "source": "PC Gamer",
      "url": "https://www.pcgamer.com/games/rpg/task-bar-hero-tier-list/"
    },
    {
      "title": "One Piece anime fans are having the biggest summer of all ti",
      "category": "游戏更新",
      "summary": "LEGO One Piece, Netflix's season 3 renewal, and the first U.S. Mugiwara Store make it a great time to be a One Piece fan.",
      "source": "Polygon",
      "url": "https://www.polygon.com/one-piece-fans-are-eating-well-right-now/"
    },
    {
      "title": "Call of Duty: Black Ops 1 and 2's Leaked PS5 Trophy List Ind",
      "category": "爆料",
      "summary": "Call of Duty: Black Ops 1 and 2 might be missing a few modes and pieces of content when they're re-released for PS4 and PS5 later this month.",
      "source": "IGN",
      "url": "https://www.ign.com/articles/call-of-duty-black-ops-1-and-2s-leaked-ps5-trophy-list-indicates-some-content-may-be-missing"
    },
    {
      "title": "Pokémon Winds & Waves rumor of 300 new Pokémon has fans divi",
      "category": "爆料",
      "summary": "Information about Pokémon Winds and Waves is scarce, leading to fans analyzing rumors for their Poké-news.",
      "source": "Polygon",
      "url": "https://www.polygon.com/pokemon-winds-waves-rumor-300-new-pokemon-pokedex-weather/"
    },
    {
      "title": "New Minecraft Update Finally Allows Players to Sit Down",
      "category": "游戏更新",
      "summary": "Minecraft's new update is getting a lot of praise for adding the simple, but long-awaited feature that lets players sit down without using mods.",
      "source": "IGN",
      "url": "https://www.ign.com/articles/new-minecraft-update-finally-allows-players-to-sit-down"
    },
    {
      "title": "Xbox layoffs hit accessibility leadership, calling into ques",
      "category": "重磅新闻",
      "summary": "Accessibility efforts have been some of Microsoft's biggest wins—but that didn't stop it from cutting accessibility leads.",
      "source": "PC Gamer",
      "url": "https://www.pcgamer.com/gaming-industry/xbox-layoffs-hit-accessibility-leadership-calling-into-question-microsofts-continued-commitment-to-accessibility-initiatives/"
    },
    {
      "title": "I played 4 hours of The Blood of Dawnwalker and it borrows a",
      "category": "重磅新闻",
      "summary": "This vampyric adventure has The Witcher coursing through its Bloodlines.",
      "source": "PC Gamer",
      "url": "https://www.pcgamer.com/games/rpg/i-played-4-hours-of-the-blood-of-dawnwalker-and-it-borrows-a-heck-of-a-lot-from-the-witcher-3-for-good-and-bad/"
    },
    {
      "title": "Fans Canceling PS Plus To Boycott Sony Killing Discs Discove",
      "category": "重磅新闻",
      "summary": "But wait, before you leave, here's a 50 percent off coupon...",
      "source": "Kotaku",
      "url": "https://kotaku.com/fans-canceling-ps-plus-to-boycott-sony-killing-discs-discover-you-can-actually-save-money-by-threatening-to-quit-2000713459"
    },
    {
      "title": "Bernie Sanders is mad about the Xbox layoffs",
      "category": "重磅新闻",
      "summary": "The senator from Vermont is pretty chapped about the price hikes, too.",
      "source": "PC Gamer",
      "url": "https://www.pcgamer.com/gaming-industry/bernie-sanders-is-mad-about-the-xbox-layoffs/"
    },
    {
      "title": "Arc Raiders’ Matchmaking Update Gives Players What They’ve A",
      "category": "发售定档",
      "summary": "The latest Arc Raiders update is out now, and alongside the opening of the Expedition 4 window and an upcoming crossover event with Embark's first-person shooter The Finals, the extraction game is getting a matchmaking overhaul that fulfills one of players' biggest wishlist items",
      "source": "GameSpot",
      "url": "https://www.gamespot.com/articles/arc-raiders-matchmaking-update-gives-players-what-theyve-always-wanted/"
    },
    {
      "title": "All Xbox studios remaining following mass layoffs and restru",
      "category": "重磅新闻",
      "summary": "Here's what we know about every studio remaining at Xbox following the company's mass layoff announcement.",
      "source": "Polygon",
      "url": "https://www.polygon.com/xbox-studio-status-2026/"
    }
  ],
  "studios": [
    {
      "company": "任天堂",
      "title": "Nintendo Expands Switch Online's Game Boy & GBA Library With",
      "summary": "Wario Land and more!Nintendo has today expanded the Switch Online Game Boy and Game Boy Advance library with four more titles.Switch Online members with a standard subscription can access the Game Boy titles, and if you also have an Expansion subscription, you'll be able to play ",
      "source": "Nintendo Life",
      "url": "https://www.nintendolife.com/news/2026/07/nintendo-expands-switch-onlines-game-boy-and-gba-library-with-four-more-titles"
    },
    {
      "company": "索尼 / SIE",
      "title": "Sony Tries To Change The Subject After Killing PlayStation D",
      "summary": "To kick off July, Sony made the surprising announcement that it plans to end support of physical discs for PlayStation games at the beginning of 2028. In the week since that news, Sony kept quiet on social media. Now, Sony has attempted to start a new conversation with gamers, bu",
      "source": "GameSpot",
      "url": "https://www.gamespot.com/articles/sony-tries-to-change-the-subject-after-killing-playstation-discs/"
    },
    {
      "company": "微软 / Xbox",
      "title": "Former Elder Scrolls Online designer laments the destruction",
      "summary": "ZeniMax Online Studios reportedly lost half its employees in yesterday's Xbox layoffs.",
      "source": "PC Gamer",
      "url": "https://www.pcgamer.com/games/mmo/former-elder-scrolls-online-designer-laments-the-destruction-of-layoffs-theres-really-no-one-left-and-no-changing-it-now/"
    },
    {
      "company": "EA / 美国艺电",
      "title": "EVE Vanguard Reinvented Its Gameplay With Some Notes from Ba",
      "summary": "While developer Fenris previously hesitated to use the term \"extraction shooter,\" that's very much the core of EVE Vanguard's Operation Avalon at the moment. You beam down to the planet in a clone body, try to collect as many resources as possible, and beam out before you get ann",
      "source": "IGN",
      "url": "https://www.ign.com/articles/eve-vanguard-reinvented-its-gameplay-with-some-notes-from-battlefield-6-hands-on-preview"
    },
    {
      "company": "育碧 / Ubisoft",
      "title": "Assassin's Creed Black Flag Resynced Steam Pre-Orders Have A",
      "summary": "Launch sales projections for Ubisoft's Assassin's Creed Black Flag remake look like a huge improvement on Assassin's Creed Shadows, the franchise's most recent release.",
      "source": "IGN",
      "url": "https://www.ign.com/articles/assassins-creed-black-flag-resynced-steam-pre-orders-have-already-beaten-skull-bones-lifetime-sales-analyst-claims"
    }
  ]
}